algosystem/__init__.py
algosystem/analysis/__init__.py
algosystem/analysis/performance.py
algosystem/analysis/portfolio.py
algosystem/analysis/risk.py
algosystem/api.py
algosystem/backtesting/__init__.py
algosystem/backtesting/dashboard/__init__.py
algosystem/backtesting/dashboard/dashboard_generator.py
algosystem/backtesting/dashboard/static/css/dashboard.css
algosystem/backtesting/dashboard/static/images/logo_transparent.png
algosystem/backtesting/dashboard/static/js/chart_factory.js
algosystem/backtesting/dashboard/static/js/dashboard.js
algosystem/backtesting/dashboard/static/js/metric_factory.js
algosystem/backtesting/dashboard/template/base_template.py
algosystem/backtesting/dashboard/template/chart_templates.py
algosystem/backtesting/dashboard/template/metric_templates.py
algosystem/backtesting/dashboard/utils/__init__.py
algosystem/backtesting/dashboard/utils/config_parser.py
algosystem/backtesting/dashboard/utils/create_pptx.py
algosystem/backtesting/dashboard/utils/data_formatter.py
algosystem/backtesting/dashboard/utils/default_config.json
algosystem/backtesting/dashboard/utils/default_config.py
algosystem/backtesting/dashboard/utils/ip_slide_generator.py
algosystem/backtesting/dashboard/utils/template.pptx
algosystem/backtesting/dashboard/web_app/__init__.py
algosystem/backtesting/dashboard/web_app/app.py
algosystem/backtesting/dashboard/web_app/available_components.py
algosystem/backtesting/dashboard/web_app/routes.py
algosystem/backtesting/dashboard/web_app/static/css/dashboard_editor.css
algosystem/backtesting/dashboard/web_app/static/js/dashboard_editor.js
algosystem/backtesting/dashboard/web_app/templates/chart_config.html
algosystem/backtesting/dashboard/web_app/templates/index.html
algosystem/backtesting/engine.py
algosystem/backtesting/metrics.py
algosystem/cli/__init__.py
algosystem/cli/commands.py
algosystem/data/__init__.py
algosystem/data/benchmark/10y_treasury.parquet
algosystem/data/benchmark/13w_treasury.parquet
algosystem-0.1.9.dist-info/entry_points.txt
algosystem-0.1.9.dist-info/METADATA
algosystem-0.1.9.dist-info/WHEEL
algosystem-0.1.9.dist-info/RECORD
